nqrduck/__init__.py
nqrduck/__main__.py
nqrduck/assets/animations.py
nqrduck/assets/icons.py
nqrduck/assets/animations/DuckKick_128x128.gif
nqrduck/assets/animations/DuckSleep_128x128.gif
nqrduck/assets/logos/ArrowLeft_12x12.png
nqrduck/assets/logos/ArrowRight_12x12.png
nqrduck/assets/logos/Attention_16x16.png
nqrduck/assets/logos/Error_16x16.png
nqrduck/assets/logos/Garbage_12x12.png
nqrduck/assets/logos/Info_16x16.png
nqrduck/assets/logos/LabMallardnbg_32x32.png
nqrduck/assets/logos/Load_16x16.png
nqrduck/assets/logos/Logo_64x32.png
nqrduck/assets/logos/Logo_full.png
nqrduck/assets/logos/New_16x16.png
nqrduck/assets/logos/Pen_12x12.png
nqrduck/assets/logos/Play_16x16.png
nqrduck/assets/logos/Pond_256_128.png
nqrduck/assets/logos/QuestionMark_16x16.png
nqrduck/assets/logos/Save_16x16.png
nqrduck/assets/logos/Settings_16x16.png
nqrduck/assets/pulseparameters/GateOff.png
nqrduck/assets/pulseparameters/GateOn.png
nqrduck/assets/pulseparameters/RXOff.png
nqrduck/assets/pulseparameters/RXOn.png
nqrduck/assets/pulseparameters/TXCustom.png
nqrduck/assets/pulseparameters/TXGauss.png
nqrduck/assets/pulseparameters/TXOff.png
nqrduck/assets/pulseparameters/TXRect.png
nqrduck/assets/pulseparameters/TXSinc.png
nqrduck/contrib/mplwidget.py
nqrduck/core/install_wizard.py
nqrduck/core/main_controller.py
nqrduck/core/main_model.py
nqrduck/core/main_view.py
nqrduck/core/main_window.py
nqrduck/core/splash_screen.py
nqrduck/core/resources/main_window.ui
nqrduck/core/resources/font/AsepriteFont.ttf
nqrduck/core/resources/font/LICENCE
nqrduck/helpers/duckwidgets.py
nqrduck/helpers/formbuilder.py
nqrduck/helpers/serializer.py
nqrduck/helpers/signalprocessing.py
nqrduck/helpers/unitconverter.py
nqrduck/helpers/validators.py
nqrduck/module/__init__.py
nqrduck/module/module.py
nqrduck/module/module_controller.py
nqrduck/module/module_model.py
nqrduck/module/module_view.py
nqrduck-0.0.12.dist-info/METADATA
nqrduck-0.0.12.dist-info/WHEEL
nqrduck-0.0.12.dist-info/entry_points.txt
nqrduck-0.0.12.dist-info/licenses/LICENSE
nqrduck-0.0.12.dist-info/RECORD
