Metadata-Version: 2.4
Name: nqrduck
Version: 0.0.12
Summary: Simple Python script to interact with various python modules used for magnetic resonance spectroscopy.
Project-URL: Homepage, https://nqrduck.cool
Project-URL: Bug Tracker, https://git.private.coffee/nqrduck/nqrduck/issues
Project-URL: Source Code, https://git.private.coffee/nqrduck/nqrduck
Author-email: jupfi <support@nqrduck.cool>
License: MIT License
License-File: LICENSE
Classifier: License :: OSI Approved :: MIT License
Classifier: Operating System :: OS Independent
Classifier: Programming Language :: Python :: 3
Requires-Python: >=3.10
Requires-Dist: matplotlib
Requires-Dist: pyqt6
Requires-Dist: pyyaml
Requires-Dist: qdarkstyle
Provides-Extra: all
Requires-Dist: nqrduck-autotm; extra == 'all'
Requires-Dist: nqrduck-broadband; extra == 'all'
Requires-Dist: nqrduck-measurement; extra == 'all'
Requires-Dist: nqrduck-pulseprogrammer; extra == 'all'
Requires-Dist: nqrduck-spectrometer; extra == 'all'
Requires-Dist: nqrduck-spectrometer-limenqr; (sys_platform == 'linux') and extra == 'all'
Requires-Dist: nqrduck-spectrometer-scout; (sys_platform == 'win32') and extra == 'all'
Requires-Dist: nqrduck-spectrometer-simulator; extra == 'all'
Provides-Extra: base
Requires-Dist: nqrduck-measurement; extra == 'base'
Requires-Dist: nqrduck-pulseprogrammer; extra == 'base'
Requires-Dist: nqrduck-spectrometer; extra == 'base'
Requires-Dist: nqrduck-spectrometer-simulator; extra == 'base'
Provides-Extra: dev
Requires-Dist: black; extra == 'dev'
Requires-Dist: pydocstyle; extra == 'dev'
Requires-Dist: pyupgrade; extra == 'dev'
Requires-Dist: ruff; extra == 'dev'
Provides-Extra: lime
Requires-Dist: nqrduck-measurement; extra == 'lime'
Requires-Dist: nqrduck-pulseprogrammer; extra == 'lime'
Requires-Dist: nqrduck-spectrometer; extra == 'lime'
Requires-Dist: nqrduck-spectrometer-limenqr; extra == 'lime'
